MANIFEST.in
README.md
babel.ini
changelog.txt
readme.txt
setup.py
ppss_auth/__init__.py
ppss_auth/constants.py
ppss_auth/models.py
ppss_auth/routes.py
ppss_auth.egg-info/PKG-INFO
ppss_auth.egg-info/SOURCES.txt
ppss_auth.egg-info/dependency_links.txt
ppss_auth.egg-info/entry_points.txt
ppss_auth.egg-info/requires.txt
ppss_auth.egg-info/top_level.txt
ppss_auth/alembic/alembic.ini
ppss_auth/alembic/env.py
ppss_auth/alembic/script.py.mako
ppss_auth/alembic/versions/20201026_52f4d4eefdfe_unique_permission_name.py
ppss_auth/alembic/versions/20201120_6c9e84ab8280_unique_user_name.py
ppss_auth/alembic/versions/20220329_44fde88fa438_creazione_colonne_per_login_history.py
ppss_auth/alembic/versions/20220331_6190d529682d_result_reason.py
ppss_auth/alembic/versions/20231016_3f4032dd2d1b_added_email_to_user.py
ppss_auth/alembic/versions/20240110_4b95deb2d91c_tabella_reset_token.py
ppss_auth/alembic/versions/20240209_7d2e85bbf831_add_otp_hash.py
ppss_auth/alembic/versions/20240304_483944c8ff05_add_phone.py
ppss_auth/alembic/versions/f724fac25359_creation.py
ppss_auth/locale/en/LC_MESSAGES/ppss_auth.mo
ppss_auth/locale/fr/LC_MESSAGES/ppss_auth.mo
ppss_auth/locale/it/LC_MESSAGES/ppss_auth.mo
ppss_auth/ppss_auth_static/loader.js
ppss_auth/ppss_auth_static/ppssauth.css
ppss_auth/ppss_auth_static/ppssauth.js
ppss_auth/ppss_auth_static/template.html
ppss_auth/ppss_auth_utils/__init__.py
ppss_auth/ppss_auth_utils/db.py
ppss_auth/ppss_auth_utils/emailclient.py
ppss_auth/ppss_auth_utils/i18n.py
ppss_auth/ppss_auth_utils/password.py
ppss_auth/ppss_auth_utils/scriptutils.py
ppss_auth/scripts/__init__.py
ppss_auth/scripts/alchemyutils.py
ppss_auth/scripts/cleanup_db.py
ppss_auth/scripts/create_user.py
ppss_auth/scripts/initialize_db.py
ppss_auth/scripts/sayauth.py
ppss_auth/scripts/upgrade_db.py
ppss_auth/templates/change.jinja2
ppss_auth/templates/change.mako
ppss_auth/templates/confirm_email.jinja2
ppss_auth/templates/confirm_email.mako
ppss_auth/templates/editgroup.jinja2
ppss_auth/templates/editgroup.mako
ppss_auth/templates/editperm.jinja2
ppss_auth/templates/editperm.mako
ppss_auth/templates/edituser.jinja2
ppss_auth/templates/edituser.mako
ppss_auth/templates/enable2fa.jinja2
