Metadata-Version: 2.1
Name: ppss_auth
Version: 0.11.2.0
Summary: simple auth scheme for pyramid, based on Mako template and sqlalchemy backend
Home-page: https://bitbucket.org/pingpongstars/ppss_auth/src/master/
Author: pdepmcp
Author-email: d.cariboni@pingpongstars.it
License: MIT
Keywords: pyramid module authentication accelerator
Classifier: Development Status :: 4 - Beta
Classifier: Intended Audience :: Developers
Classifier: Operating System :: OS Independent
Classifier: Framework :: Pyramid
Classifier: Topic :: Internet :: WWW/HTTP :: Session
Classifier: Programming Language :: Python :: 3.6
Requires-Python: >=3.6
Requires-Dist: SQLAlchemy==1.4.51
Requires-Dist: pyramid_mako
Requires-Dist: pyramid_beaker
Requires-Dist: pyramid_jinja2
Requires-Dist: alembic
Requires-Dist: cryptography
Requires-Dist: pyotp
Requires-Dist: qrcode
Requires-Dist: requests
